idataapi_transform/__init__.py
idataapi_transform/cli.py
idataapi_transform/DataProcess/ProcessFactory.py
idataapi_transform/DataProcess/__init__.py
idataapi_transform/DataProcess/Config/ConnectorConfig.py
idataapi_transform/DataProcess/Config/DefaultValue.py
idataapi_transform/DataProcess/Config/ESConfig.py
idataapi_transform/DataProcess/Config/LogConfig.py
idataapi_transform/DataProcess/Config/MainConfig.py
idataapi_transform/DataProcess/Config/__init__.py
idataapi_transform/DataProcess/Config/ConfigUtil/AsyncHelper.py
idataapi_transform/DataProcess/Config/ConfigUtil/BaseConfig.py
idataapi_transform/DataProcess/Config/ConfigUtil/GetterConfig.py
idataapi_transform/DataProcess/Config/ConfigUtil/WriterConfig.py
idataapi_transform/DataProcess/Config/ConfigUtil/__init__.py
idataapi_transform/DataProcess/DataGetter/APIGetter.py
idataapi_transform/DataProcess/DataGetter/BaseGetter.py
idataapi_transform/DataProcess/DataGetter/CSVGetter.py
idataapi_transform/DataProcess/DataGetter/ESGetter.py
idataapi_transform/DataProcess/DataGetter/JsonGetter.py
idataapi_transform/DataProcess/DataGetter/MongoGetter.py
idataapi_transform/DataProcess/DataGetter/MySQLGetter.py
idataapi_transform/DataProcess/DataGetter/RedisGetter.py
idataapi_transform/DataProcess/DataGetter/XLSXGetter.py
idataapi_transform/DataProcess/DataGetter/__init__.py
idataapi_transform/DataProcess/DataWriter/BaseWriter.py
idataapi_transform/DataProcess/DataWriter/CSVWriter.py
idataapi_transform/DataProcess/DataWriter/ESWriter.py
idataapi_transform/DataProcess/DataWriter/JsonWriter.py
idataapi_transform/DataProcess/DataWriter/KafkaWriter.py
idataapi_transform/DataProcess/DataWriter/MongoWriter.py
idataapi_transform/DataProcess/DataWriter/MySQLWriter.py
idataapi_transform/DataProcess/DataWriter/RedisWriter.py
idataapi_transform/DataProcess/DataWriter/TXTWriter.py
idataapi_transform/DataProcess/DataWriter/XLSXWriter.py
idataapi_transform/DataProcess/DataWriter/__init__.py
idataapi_transform-2.0.2.dist-info/entry_points.txt
idataapi_transform-2.0.2.dist-info/LICENSE
idataapi_transform-2.0.2.dist-info/WHEEL
idataapi_transform-2.0.2.dist-info/METADATA
idataapi_transform-2.0.2.dist-info/RECORD
