Metadata-Version: 2.1
Name: idataapi-transform
Version: 2.0.2
Summary: convert data from a format to another format, read or write from file or database, suitable for iDataAPI
Home-page: https://github.com/zpoint/idataapi-transform
Keywords: idataapi transform
Author: zpoint
Author-email: zp0int@qq.com
Requires-Python: >=3.5.2
Classifier: License :: OSI Approved :: MIT License
Requires-Dist: aiohttp
Requires-Dist: openpyxl
Requires-Dist: elasticsearch-async
Requires-Dist: aioredis
Requires-Dist: confluent_kafka
